DaxueBaKaliLinuxAnquanShentouJiaochengFix1/README.md
DaxueBaKaliLinuxAnquanShentouJiaochengFix1/__init__.py
DaxueBaKaliLinuxAnquanShentouJiaochengFix1/__main__.py
DaxueBaKaliLinuxAnquanShentouJiaochengFix1/file.epub
DaxueBaKaliLinuxAnquanShentouJiaochengFix1/index.html
DaxueBaKaliLinuxAnquanShentouJiaochengFix1/css/__init__.py
DaxueBaKaliLinuxAnquanShentouJiaochengFix1/css/annotations.css
DaxueBaKaliLinuxAnquanShentouJiaochengFix1/css/main.css
DaxueBaKaliLinuxAnquanShentouJiaochengFix1/css/normalize.css
DaxueBaKaliLinuxAnquanShentouJiaochengFix1/css/popup.css
DaxueBaKaliLinuxAnquanShentouJiaochengFix1/font/__init__.py
DaxueBaKaliLinuxAnquanShentouJiaochengFix1/font/fontello.eot
DaxueBaKaliLinuxAnquanShentouJiaochengFix1/font/fontello.svg
DaxueBaKaliLinuxAnquanShentouJiaochengFix1/font/fontello.ttf
DaxueBaKaliLinuxAnquanShentouJiaochengFix1/font/fontello.woff
DaxueBaKaliLinuxAnquanShentouJiaochengFix1/img/__init__.py
DaxueBaKaliLinuxAnquanShentouJiaochengFix1/img/annotator-glyph-sprite.png
DaxueBaKaliLinuxAnquanShentouJiaochengFix1/img/annotator-icon-sprite.png
DaxueBaKaliLinuxAnquanShentouJiaochengFix1/img/apple-touch-icon.png
DaxueBaKaliLinuxAnquanShentouJiaochengFix1/img/cancelfullscreen.png
DaxueBaKaliLinuxAnquanShentouJiaochengFix1/img/close.png
DaxueBaKaliLinuxAnquanShentouJiaochengFix1/img/fullscreen.png
DaxueBaKaliLinuxAnquanShentouJiaochengFix1/img/loader.gif
DaxueBaKaliLinuxAnquanShentouJiaochengFix1/img/menu-icon.png
DaxueBaKaliLinuxAnquanShentouJiaochengFix1/img/save.png
DaxueBaKaliLinuxAnquanShentouJiaochengFix1/img/saved.png
DaxueBaKaliLinuxAnquanShentouJiaochengFix1/img/settings-s.png
DaxueBaKaliLinuxAnquanShentouJiaochengFix1/img/settings.png
DaxueBaKaliLinuxAnquanShentouJiaochengFix1/img/star.png
DaxueBaKaliLinuxAnquanShentouJiaochengFix1/js/__init__.py
DaxueBaKaliLinuxAnquanShentouJiaochengFix1/js/epub.js
DaxueBaKaliLinuxAnquanShentouJiaochengFix1/js/epub.min.js
DaxueBaKaliLinuxAnquanShentouJiaochengFix1/js/epub.min.map
daxue_ba_kali_linux_anquan_shentou_jiaocheng_fix1-2024.3.2.0.dist-info/METADATA
daxue_ba_kali_linux_anquan_shentou_jiaocheng_fix1-2024.3.2.0.dist-info/WHEEL
daxue_ba_kali_linux_anquan_shentou_jiaocheng_fix1-2024.3.2.0.dist-info/entry_points.txt
daxue_ba_kali_linux_anquan_shentou_jiaocheng_fix1-2024.3.2.0.dist-info/top_level.txt
daxue_ba_kali_linux_anquan_shentou_jiaocheng_fix1-2024.3.2.0.dist-info/RECORD
